taiga_contrib_google_sso/__init__.py
taiga_contrib_google_sso/apps.py
taiga_contrib_google_sso/connector.py
taiga_contrib_google_sso/services.py
taiga_contrib_google_sso-1.1.0.dist-info/LICENSE
taiga_contrib_google_sso-1.1.0.dist-info/METADATA
taiga_contrib_google_sso-1.1.0.dist-info/WHEEL
taiga_contrib_google_sso-1.1.0.dist-info/top_level.txt
taiga_contrib_google_sso-1.1.0.dist-info/RECORD
